askgoogle/__init__.py
askgoogle/askgoogle.py
AskGoogle-1.0.3.dist-info/LICENSE.txt
AskGoogle-1.0.3.dist-info/METADATA
AskGoogle-1.0.3.dist-info/WHEEL
AskGoogle-1.0.3.dist-info/top_level.txt
AskGoogle-1.0.3.dist-info/RECORD
