Metadata-Version: 2.1
Name: AskGoogle
Version: 1.0.3
Summary: Automatically redirects to Google when an exception is thrown.
Home-page: https://github.com/NathanTW0219/AskGoogle.py
Author: NathanTW0219
License: MIT
License-File: LICENSE.txt
